{
    "plutus": {
        "branch": "master",
        "description": "The Plutus language implementation and tools",
        "homepage": "",
        "owner": "input-output-hk",
        "repo": "plutus",
        "rev": "f7466c86fe3afc593746e44257adbf7785f7cedb",
        "sha256": "0vnv7j0ysmyffwkmbhy05a8iw2n8xvdxcvy3lq8vg08zw8c3nvan",
        "type": "tarball",
        "url": "https://github.com/input-output-hk/plutus/archive/refs/tags/v2021-09-10.tar.gz",
        "url_template": "https://github.com/<owner>/<repo>/archive/<rev>.tar.gz"
    }
}
